odoo9_addon_account_analytic_required-9.0.1.0.0.99.dev13-py3.8-nspkg.pth
odoo_addons/account_analytic_required/README.rst
odoo_addons/account_analytic_required/__init__.py
odoo_addons/account_analytic_required/__openerp__.py
odoo_addons/account_analytic_required/i18n/account_analytic_required.pot
odoo_addons/account_analytic_required/i18n/ar.po
odoo_addons/account_analytic_required/i18n/ca.po
odoo_addons/account_analytic_required/i18n/es.po
odoo_addons/account_analytic_required/i18n/fr.po
odoo_addons/account_analytic_required/i18n/nl.po
odoo_addons/account_analytic_required/models/__init__.py
odoo_addons/account_analytic_required/models/account.py
odoo_addons/account_analytic_required/static/description/icon.png
odoo_addons/account_analytic_required/tests/__init__.py
odoo_addons/account_analytic_required/tests/test_account_analytic_required.py
odoo_addons/account_analytic_required/views/account.xml
odoo9_addon_account_analytic_required-9.0.1.0.0.99.dev13.dist-info/METADATA
odoo9_addon_account_analytic_required-9.0.1.0.0.99.dev13.dist-info/WHEEL
odoo9_addon_account_analytic_required-9.0.1.0.0.99.dev13.dist-info/namespace_packages.txt
odoo9_addon_account_analytic_required-9.0.1.0.0.99.dev13.dist-info/top_level.txt
odoo9_addon_account_analytic_required-9.0.1.0.0.99.dev13.dist-info/RECORD
